arxiv_retriever/__init__.py
arxiv_retriever/cli.py
arxiv_retriever/fetcher.py
arxiv_retriever/rag/__init__.py
arxiv_retriever/rag/extractor.py
arxiv_retriever/rag/llm_interface.py
arxiv_retriever/utils.py
arxiv_retriever-1.3.2.dist-info/LICENSE
arxiv_retriever-1.3.2.dist-info/METADATA
arxiv_retriever-1.3.2.dist-info/WHEEL
arxiv_retriever-1.3.2.dist-info/entry_points.txt
arxiv_retriever-1.3.2.dist-info/RECORD
