Metadata-Version: 2.1
Name: arxiv_retriever
Version: 1.3.2
Summary: "Automate your ArXiv paper search, retrieval, and summarization process."
Home-page: https://github.com/MimicTester1307/arxiv_retriever
License: MIT
Keywords: arxiv,cli,research
Author: Excel Chukwu
Author-email: excel.chukwu1.0@gmail.com
Requires-Python: >=3.8,<4.0
Classifier: License :: OSI Approved :: MIT License
Classifier: Programming Language :: Python :: 3
Classifier: Programming Language :: Python :: 3.8
Classifier: Programming Language :: Python :: 3.9
Classifier: Programming Language :: Python :: 3.10
Classifier: Programming Language :: Python :: 3.11
Classifier: Programming Language :: Python :: 3.12
Requires-Dist: certifi (>=2024.7.4)
Requires-Dist: charset-normalizer (>=3.3.2)
Requires-Dist: click (>=8.1.7)
Requires-Dist: httpx (>=0.27.0,<0.28.0)
Requires-Dist: idna (>=3.7)
Requires-Dist: iniconfig (>=2.0.0)
Requires-Dist: markdown-it-py (>=3.0.0)
Requires-Dist: mdurl (>=0.1.2)
Requires-Dist: openai (>=1.36.0,<2.0.0)
Requires-Dist: packaging (>=24.1)
Requires-Dist: pluggy (>=1.5.0)
Requires-Dist: pygments (>=2.18.0)
Requires-Dist: python-dotenv (>=1.0.1,<2.0.0)
Requires-Dist: requests (>=2.32.3)
Requires-Dist: rich (>=13.7.1)
Requires-Dist: shellingham (>=1.5.4)
Requires-Dist: trio (>=0.26.0,<0.27.0)
Requires-Dist: typer (>=0.12.3)
Requires-Dist: typing-extensions (>=4.12.2)
Requires-Dist: urllib3 (>=2.2.2)
Project-URL: Repository, https://github.com/MimicTester1307/arxiv_retriever
